pypidtune/__init__.py
pypidtune/common.py
pypidtune/logger.py
pypidtune/process_emulator.py
pypidtune/sim.py
pypidtune/tuner.py
pypidtune-0.2.1.dist-info/LICENSE
pypidtune-0.2.1.dist-info/METADATA
pypidtune-0.2.1.dist-info/WHEEL
pypidtune-0.2.1.dist-info/top_level.txt
pypidtune-0.2.1.dist-info/RECORD
