Metadata-Version: 2.1
Name: pypidtune
Version: 0.2.1
Summary: PID tuner, logger, simulator and process emulator
Home-page: https://github.com/PIDTuningIreland/pypidtune
Author: PIDTuningIreland
Author-email: pidtuningireland@gmail.com
License: MIT
Keywords: PID Tuner
Classifier: Development Status :: 5 - Production/Stable
Classifier: Intended Audience :: Information Technology
Classifier: Programming Language :: Python :: 3.8
Classifier: Programming Language :: Python :: 3.9
Classifier: Programming Language :: Python :: 3.10
Classifier: Programming Language :: Python :: 3.11
Classifier: Programming Language :: Python :: 3.12
Classifier: Operating System :: MacOS :: MacOS X
Classifier: Operating System :: Microsoft :: Windows
Classifier: Operating System :: POSIX :: Linux
License-File: LICENSE
Requires-Dist: scipy >=1.8.0
Requires-Dist: numpy >=1.22.1
Requires-Dist: matplotlib >=3.5.1
Requires-Dist: pylogix >=0.8.0
Requires-Dist: asyncua >=0.9.92
